tabular_data_loader-0.1.2.dist-info/METADATA
tabular_data_loader-0.1.2.dist-info/WHEEL
tabular_data_loader/__init__.py
tabular_data_loader/tabular_data_loader.cpython-38-x86_64-linux-gnu.so
tabular_data_loader-0.1.2.dist-info/RECORD
