Metadata-Version: 2.4
Name: tabular_data_loader
Version: 0.1.2
Classifier: Programming Language :: Rust
Classifier: Programming Language :: Python :: Implementation :: CPython
Classifier: Programming Language :: Python :: 3.10
Classifier: Programming Language :: Python :: 3.11
Classifier: Programming Language :: Python :: 3.12
Classifier: Programming Language :: Python :: 3.13
Requires-Dist: openpyxl>=3.1.3 ; extra == 'dev'
Requires-Dist: pytest>=7.0.0 ; extra == 'dev'
Provides-Extra: dev
Summary: A Rust-powered library for loading tabular data from CSV and Excel files
Author-email: Cristi Boboc <cristi@cbsoft.ro>
License: MIT
Requires-Python: >=3.10
Project-URL: Changelog, https://gitlab.com/bapp-cloud/packages/rust-tabular-loader/-/blob/main/CHANGELOG.md
Project-URL: Repository, https://gitlab.com/bapp-cloud/packages/rust-tabular-loader
